django_style/__init__.py
django_style/apps.py
django_style/constants.py
django_style/context_processors.py
django_style/nanodjango.py
django_style/utils.py
django_style/static/django_style/bootstrap/styles.css
django_style/static/django_style/simple/close.svg
django_style/static/django_style/simple/cloxse.svg
django_style/static/django_style/simple/menu.svg
django_style/static/django_style/simple/styles.css
django_style/static/django_style/tailwind/site.js
django_style/templates/base.html
django_style/templates/django_style/bootstrap/base.html
django_style/templates/django_style/simple/base.html
django_style/templates/django_style/tailwind/base.html
django_style-0.1.2.dist-info/licenses/LICENSE
django_style-0.1.2.dist-info/METADATA
django_style-0.1.2.dist-info/WHEEL
django_style-0.1.2.dist-info/entry_points.txt
django_style-0.1.2.dist-info/top_level.txt
django_style-0.1.2.dist-info/RECORD
