Metadata-Version: 2.4
Name: django-style
Version: 0.1.2
Summary: Basic tasteful designs for your Django project
Author-email: Richard Terry <code@radiac.net>
License-Expression: BSD-3-Clause
Project-URL: Homepage, https://radiac.net/projects/django-style/
Project-URL: Documentation, https://django-style.readthedocs.io/en/latest/
Project-URL: Source, https://github.com/radiac/django-style
Project-URL: Bug Tracker, https://github.com/radiac/django-style/issues
Keywords: django,style,theme
Classifier: Development Status :: 4 - Beta
Classifier: Framework :: Django
Classifier: Programming Language :: Python :: 3
Classifier: Operating System :: OS Independent
Requires-Python: >=3.7
License-File: LICENSE
Requires-Dist: Django>=4.2
Dynamic: license-file
